README.rst
setup.py
wishbone_decode_msgpack/__init__.py
wishbone_decode_msgpack/msgpackdecode.py
wishbone_decode_msgpack.egg-info/PKG-INFO
wishbone_decode_msgpack.egg-info/SOURCES.txt
wishbone_decode_msgpack.egg-info/dependency_links.txt
wishbone_decode_msgpack.egg-info/entry_points.txt
wishbone_decode_msgpack.egg-info/namespace_packages.txt
wishbone_decode_msgpack.egg-info/not-zip-safe
wishbone_decode_msgpack.egg-info/requires.txt
wishbone_decode_msgpack.egg-info/top_level.txt